xksqlite/__init__.py
xksqlite/sqlite.py
xksqlite-2.0.0.dist-info/licenses/LICENSE
xksqlite-2.0.0.dist-info/METADATA
xksqlite-2.0.0.dist-info/WHEEL
xksqlite-2.0.0.dist-info/top_level.txt
xksqlite-2.0.0.dist-info/RECORD
