Metadata-Version: 2.4
Name: xksqlite
Version: 2.0.0
Summary: 数据库的连接工具，包括记录报错和日志
Author-email: ZhaoYuanKang <1756972525@qq.com>
License: MIT License
Project-URL: Personal website, http://121.37.247.246:200/
Requires-Python: >=3.7
License-File: LICENSE
Requires-Dist: xiaokang==1.0.0
Dynamic: license-file
